README.md
setup.cfg
setup.py
mock_base/__init__.py
mock_base/fake_device.py
mock_base/mock_auth.py
mock_base/mock_messaging.py
mock_base/mock_storage.py
mock_base/mock_store.py
mock_base.egg-info/PKG-INFO
mock_base.egg-info/SOURCES.txt
mock_base.egg-info/dependency_links.txt
mock_base.egg-info/top_level.txt
mock_base/_firestore/__firestore_abstract.py
mock_base/_firestore/__init__.py
mock_base/_firestore/_db.py
mock_base/_firestore/_fx.py
mock_base/_firestore/mockstore.py
mock_base/_messaging/__init__.py
mock_base/_messaging/messaging.py