Metadata-Version: 1.0
Name: mock-base
Version: 0.0.5
Summary: mock for firebase_admin
Home-page: https://github.com/SpinaNico/python-mock-base
Author: Spina Nico
Author-email: spinanico93@gmail.com
License: UNKNOWN
Platform: UNKNOWN
